life3d_rgb/__init__.py
life3d_rgb/__main__.py
life3d_rgb/cli.py
life3d_rgb/death_switch.py
life3d_rgb/engine.py
life3d_rgb/ui.py
life3d_rgb/ui_main.py
life3d_rgb/visualize.py
life3d_rgb/presets/__init__.py
life3d_rgb/presets/example_config.json
life3d_rgb/presets/sample.json
life3d_rgb/presets/starburst.json
life3d_rgb-0.7.4.data/data/life3d_rgb/presets/__init__.py
life3d_rgb-0.7.4.data/data/life3d_rgb/presets/example_config.json
life3d_rgb-0.7.4.data/data/life3d_rgb/presets/sample.json
life3d_rgb-0.7.4.data/data/life3d_rgb/presets/starburst.json
life3d_rgb-0.7.4.dist-info/METADATA
life3d_rgb-0.7.4.dist-info/WHEEL
life3d_rgb-0.7.4.dist-info/entry_points.txt
life3d_rgb-0.7.4.dist-info/licenses/LICENSE
life3d_rgb-0.7.4.dist-info/RECORD
