Metadata-Version: 2.4
Name: life3d-rgb
Version: 0.7.4
Summary: 3D cellular automata (26-neighbor) with RGB inheritance, mutations, GIF output, and optional Tk UI.
Project-URL: Homepage, https://github.com/anthropics/claude-code
Project-URL: Repository, https://github.com/anthropics/claude-code
Project-URL: Issues, https://github.com/anthropics/claude-code/issues
Project-URL: Documentation, https://github.com/anthropics/claude-code#readme
Author-email: Rami Pinku <contact@newrelam.co>
License: Apache-2.0
License-File: LICENSE
Keywords: 3D,RGB,art,cellular-automata,generative,matplotlib,simulation,voxel
Classifier: Development Status :: 4 - Beta
Classifier: Environment :: Console
Classifier: Environment :: X11 Applications :: Qt
Classifier: Intended Audience :: End Users/Desktop
Classifier: Intended Audience :: Science/Research
Classifier: License :: OSI Approved :: Apache Software License
Classifier: Programming Language :: Python :: 3
Classifier: Programming Language :: Python :: 3.10
Classifier: Programming Language :: Python :: 3.11
Classifier: Programming Language :: Python :: 3.12
Classifier: Programming Language :: Python :: 3.13
Classifier: Topic :: Artistic Software
Classifier: Topic :: Games/Entertainment :: Simulation
Classifier: Topic :: Multimedia :: Graphics
Classifier: Topic :: Scientific/Engineering :: Visualization
Requires-Python: >=3.10
Requires-Dist: imageio<3.0,>=2.31
Requires-Dist: matplotlib<4.0,>=3.7
Requires-Dist: numpy<3.0,>=1.24
Provides-Extra: dev
Requires-Dist: black>=23.0; extra == 'dev'
Requires-Dist: isort>=5.0; extra == 'dev'
Requires-Dist: mypy>=1.0; extra == 'dev'
Requires-Dist: pytest-cov>=4.0; extra == 'dev'
Requires-Dist: pytest>=7.0; extra == 'dev'
Provides-Extra: ui
